Workbook

Sheet Как пользоваться
A1: СоздайСвоюПесню — экономика
A3: Жёлтые ячейки | B3: Ваши цифры — меняйте сами
A4: Синий текст | B4: Тоже ввод (оценки до уточнения)
A5: Чёрные формулы | B5: Пересчитываются автоматически
A7: Листы:
A8: Ввод | B8: Главные допущения (курс, API, налоги)
A9: Фикс | B9: Постоянные расходы ₽/мес
A10: Пакеты | B10: Текущие тарифы и маржа
A11: Промо | B11: Скидка % для беты — маржа после GP+НПД
A12: Калькулятор | B12: Точка безубыточности
A13: Реклама | B13: CAC / LTV / пробные
A14: Балансы | B14: Журнал пополнений API
A15: Подписка | B15: Черновик планов
A17: Текст для ассистента: | B17: docs/biznes/ЭКОНОМИКА.txt §11
A18: Обновлено: | B18: 15 июля 2026

Sheet Ввод
A1: Допущения (меняйте жёлтые/синие ячейки)
A3: Параметр | B3: Значение | C3: Ключ
A4: Курс USD → RUB (справочно) | B4: 95 | C4: usd_rub
A5: Suno, ₽/нота (15 cr, 1000cr=500₽) | B5: 7.5 | C5: suno_rub
A6: YandexGPT, ₽/нота | B6: 5 | C6: yandex_rub
A7: S3, ₽/нота | B7: 0.5 | C7: s3_rub
A8: Брак/retry, % к API | B8: 0.12 | C8: waste_pct
A9: Эквайринг GetPlatinum, % | B9: 0.035 | C9: gp_pct
A10: НПД, % с выручки | B10: 0.04 | C10: npd_pct
A11: Платных нот в месяц (прогноз) | B11: 50 | C11: notes_month
A12: Пробных генераций в месяц | B12: 100 | C12: trials_month
A13: Себест. пробной, ₽ | B13: 15 | C13: trial_cost
A15: Переменная себест. 1 ноты, ₽ | B15: =B5+B6+B7+(B5+B6+B7)*B9
A16: Итого фикс ₽/мес (с листа Фикс) | B16: =Фикс!B12
A17: Фикс на 1 ноту, ₽ | B17: =IF(B11>0,B16/B11,0)

Sheet Фикс
A1: Постоянные расходы, ₽/мес
A3: Статья | B3: ₽/мес | C3: Примечание
A4: VPS (сейчас копейки / заложить рост) | B4: 1500 | C4: заполнить
A5: Домен sozdaipesnu.ru (продление/12) | B5: 50 | C5: заполнить
A6: Почта REG.RU Mail-1 | B6: 200 | C6: заполнить
A7: S3 REG.RU Object Storage | B7: 100 | C7: заполнить
A8: Yandex Cloud (мин./факт) | B8: 200 | C8: заполнить
A9: Прочее (мониторинг и т.п.) | B9: 100 | C9: заполнить
A11: CAPEX разово (не в месяц)
A12: ИТОГО фикс ₽/мес | B12: =SUM(B4:B9)

Sheet Пакеты
A1: Пакеты нот (как на сайте v2.11.42)
A3: ID | B3: Нот | C3: Цена ₽ | D3: ₽/нота | E3: Себест. ₽ | F3: Маржа ₽ | G3: Маржа %
A4: notes_1 | B4: 1 | C4: 149 | D4: =C4/B4 | E4: =B4*(Ввод!$B$15+Ввод!$B$17)+C4*(Ввод!$B$10+Ввод!$B$11) | F4: =C4-E4 | G4: =IF(C4>0,F4/C4,0)
A5: notes_3 | B5: 3 | C5: 375 | D5: =C5/B5 | E5: =B5*(Ввод!$B$15+Ввод!$B$17)+C5*(Ввод!$B$10+Ввод!$B$11) | F5: =C5-E5 | G5: =IF(C5>0,F5/C5,0)
A6: notes_5 | B6: 5 | C6: 599 | D6: =C6/B6 | E6: =B6*(Ввод!$B$15+Ввод!$B$17)+C6*(Ввод!$B$10+Ввод!$B$11) | F6: =C6-E6 | G6: =IF(C6>0,F6/C6,0)
A7: notes_10 | B7: 10 | C7: 899 | D7: =C7/B7 | E7: =B7*(Ввод!$B$15+Ввод!$B$17)+C7*(Ввод!$B$10+Ввод!$B$11) | F7: =C7-E7 | G7: =IF(C7>0,F7/C7,0)
A9: Жёсткий пол ₽/нота (ориентир) | B9: 45

Sheet Промо
A1: Промо для тестеров (GetPlatinum). Жёлтое — меняйте.
A3: Скидка промокода, % | B3: 0.3
A4: Перем. себест. 1 ноты ₽ (из Ввод B15) | B4: =Ввод!B15
A5: GP % + НПД % | B5: =Ввод!B10+Ввод!B11
A6: Рабочий пол ₽/нота (запас) | B6: 99
A8: Пакет | B8: Нот | C8: Цена ₽ | D8: После скидки ₽ | E8: ₽/нота | F8: Себест. нот ₽ | G8: Маржа ₽ | H8: ₽/н ≥ пол?
A9: notes_1 | B9: 1 | C9: 149 | D9: =C9*(1-$B$3) | E9: =D9/B9 | F9: =B9*$B$4+D9*$B$5 | G9: =D9-F9 | H9: =IF(E9>=$B$6,"ДА","нет")
A10: notes_3 | B10: 3 | C10: 375 | D10: =C10*(1-$B$3) | E10: =D10/B10 | F10: =B10*$B$4+D10*$B$5 | G10: =D10-F10 | H10: =IF(E10>=$B$6,"ДА","нет")
A11: notes_5 | B11: 5 | C11: 599 | D11: =C11*(1-$B$3) | E11: =D11/B11 | F11: =B11*$B$4+D11*$B$5 | G11: =D11-F11 | H11: =IF(E11>=$B$6,"ДА","нет")
A12: notes_10 | B12: 10 | C12: 899 | D12: =C12*(1-$B$3) | E12: =D12/B12 | F12: =B12*$B$4+D12*$B$5 | G12: =D12-F12 | H12: =IF(E12>=$B$6,"ДА","нет")
A14: Рекомендация (текст)
A15: Бета: 30–40% комфортно. 50% ок при малом числе тестеров. >60% на notes_10 — тонкая маржа. 100% только админка ±ноты (маркетинг).
A16: См. docs/biznes/ЭКОНОМИКА.txt §11

Sheet Калькулятор
A1: Сводка месяца
A3: Показатель | B3: Значение
A4: Фикс ₽/мес | B4: =Фикс!B12
A5: Пробные × себест. | B5: =Ввод!B12*Ввод!B13
A6: Реклама ₽/мес | B6: 10000
A7: Итого затрат до маржи | B7: =B4+B5+B6
A8: Средняя цена ноты ₽ | B8: 220
A9: Переменная + фикс/нота ₽ | B9: =Ввод!B15+Ввод!B17
A10: Маржа на ноту ₽ | B10: =B9*(1-Ввод!B10-Ввод!B11)-B10
A11: Нот для безубыточности | B11: =IF(B11>0,B7/B11,0)

Sheet Реклама
A1: CAC / LTV
A3: Рекламный бюджет ₽ | B3: 10000
A4: Платящих клиентов | B4: 20
A5: CAC ₽ | B5: =IF(B4>0,B3/B4,0)
A6: Средний чек ₽ | B6: 500
A7: Покупок на клиента | B7: 1.5
A8: LTV ₽ | B8: =B6*B7
A9: LTV / CAC | B9: =IF(B5>0,B8/B5,0)
A10: Ок? (LTV > 3×CAC) | B10: =IF(B9>=3,"ДА","НЕТ")

Sheet Балансы
A1: Журнал пополнений и алерты
A3: Дата | B3: Сервис | C3: Сумма | D3: Баланс после | E3: Алерт если | F3: Примечание
B4: sunoapi.org | E4: credits < 100
B5: ApiPass | E5: $ < 5
B6: Yandex Cloud | E6: ₽ < 100
B7: REG.RU S3 | E7: квота 80%

Sheet Подписка
A1: Черновик подписки
A3: План | B3: Нот/мес | C3: Цена ₽ | D3: ₽/нота | E3: Сгорают?
A4: Старт | B4: 5 | C4: 499 | D4: =C4/B4 | E4: да
A5: Базовый | B5: 15 | C5: 1199 | D5: =C5/B5 | E5: да
A6: Про | B6: 40 | C6: 2499 | D6: =C6/B6 | E6: да
